{
  "db_name": "PostgreSQL",
  "query": "SELECT * FROM read_states WHERE user_id = $1 AND channel_id = $2;",
  "describe": {
    "columns": [
      {
        "ordinal": 0,
        "name": "user_id",
        "type_info": "Text"
      },
      {
        "ordinal": 1,
        "name": "channel_id",
        "type_info": "Text"
      },
      {
        "ordinal": 2,
        "name": "last_message_id",
        "type_info": "Text"
      },
      {
        "ordinal": 3,
        "name": "mentions",
        "type_info": "Int4"
      }
    ],
    "parameters": {
      "Left": [
        "Text",
        "Text"
      ]
    },
    "nullable": [
      false,
      false,
      false,
      false
    ]
  },
  "hash": "c4aa8c6d7e5a567a6fb14065e0860e4b57d30092803794c46c3ad758e5d7147c"
}
